blyadogram/__init__.py
blyadogram/bot/__init__.py
blyadogram/bot/bot.py
blyadogram/bot/methods.py
blyadogram/database/__init__.py
blyadogram/database/base.py
blyadogram/database/memory.py
blyadogram/database/postgres.py
blyadogram/database/sqlite.py
blyadogram/dispatcher/__init__.py
blyadogram/dispatcher/dispatcher.py
blyadogram/dispatcher/router.py
blyadogram/dispatcher/telegram_update.py
blyadogram/enums.py
blyadogram/exceptions.py
blyadogram/filters/__init__.py
blyadogram/filters/base.py
blyadogram/filters/command.py
blyadogram/filters/content_type.py
blyadogram/filters/data.py
blyadogram/filters/state_filter.py
blyadogram/filters/text.py
blyadogram/fsm/__init__.py
blyadogram/fsm/context.py
blyadogram/fsm/state.py
blyadogram/fsm/storage/base.py
blyadogram/fsm/storage/memory.py
blyadogram/fsm/storage/redis.py
blyadogram/middlewares/__init__.py
blyadogram/middlewares/base.py
blyadogram/middlewares/database.py
blyadogram/middlewares/handler_middlewares.py
blyadogram/middlewares/throttling.py
blyadogram/scheduler/__init__.py
blyadogram/scheduler/scheduler.py
blyadogram/types/__init__.py
blyadogram/types/callback_query.py
blyadogram/types/chat.py
blyadogram/types/inline_keyboard.py
blyadogram/types/input_file.py
blyadogram/types/message.py
blyadogram/types/photo.py
blyadogram/types/reply_keyboard.py
blyadogram/types/update.py
blyadogram/types/user.py
blyadogram/types/video.py
blyadogram-2.0.0.dist-info/METADATA
blyadogram-2.0.0.dist-info/WHEEL
blyadogram-2.0.0.dist-info/RECORD
