Metadata-Version: 2.1
Name: blyadogram
Version: 2.0.0
Summary: 
Author: GG
Requires-Python: >=3.11,<4.0
Classifier: Programming Language :: Python :: 3
Classifier: Programming Language :: Python :: 3.11
Requires-Dist: aiohttp (>=3.8.6,<4.0.0)
Requires-Dist: aiosqlite (>=0.19.0,<0.20.0)
Requires-Dist: asyncpg (>=0.28.0,<0.29.0)
Requires-Dist: redis (>=5.0.1,<6.0.0)
